robust_extraction/__init__.py
robust_extraction/__init__.pyi
robust_extraction/contours/__init__.py
robust_extraction/contours/__init__.pyi
robust_extraction/contours/contours.py
robust_extraction/contours/rois.py
robust_extraction/contours/types.py
robust_extraction/lines/__init__.py
robust_extraction/lines/directions.py
robust_extraction/lines/extract.py
robust_extraction/lines/instersections.py
robust_extraction/lines/points.py
robust_extraction/lines/cluster/__init__.py
robust_extraction/lines/cluster/inclination.py
robust_extraction/lines/cluster/collinear/__init__.py
robust_extraction/lines/cluster/collinear/clustering.py
robust_extraction/lines/cluster/collinear/metrics.py
robust_extraction/lines/cluster/collinear/segmentation.py
robust_extraction/lines/coverage/__init__.py
robust_extraction/lines/coverage/coverage.py
robust_extraction/lines/draw/__init__.py
robust_extraction/lines/draw/clustered.py
robust_extraction/lines/poly/__init__.py
robust_extraction/lines/poly/intersections.py
robust_extraction/lines/poly/poly.py
robust_extraction/manual/__init__.py
robust_extraction/manual/_correct.py
robust_extraction/manual/_extract.py
robust_extraction/match1d/__init__.py
robust_extraction/match1d/st_lap.py
robust_extraction/perspective/__init__.py
robust_extraction/perspective/__init__.pyi
robust_extraction/perspective/perspective.py
robust_extraction/perspective/perspective2.py
robust_extraction/perspective/types.py
robust_extraction/pipeline/__init__.py
robust_extraction/pipeline/ret.py
robust_extraction/pipeline/v6.py
robust_extraction/pipeline/v7.py
robust_extraction/templates/__init__.py
robust_extraction/templates/__init__.pyi
robust_extraction/templates/templates.py
robust_extraction/templates/_models/__init__.py
robust_extraction/templates/_models/__init__.pyi
robust_extraction/templates/_models/_models.py
robust_extraction/templates/_models/andorra.py
robust_extraction/templates/_models/fcde.py
robust_extraction/templates/_models/id.py
robust_extraction-0.2.4.dist-info/METADATA
robust_extraction-0.2.4.dist-info/WHEEL
robust_extraction-0.2.4.dist-info/top_level.txt
robust_extraction-0.2.4.dist-info/RECORD
